nestipy_dynamic_module/__init__.py
nestipy_dynamic_module/builder.py
nestipy_dynamic_module/module/__init__.py
nestipy_dynamic_module/module/consumer.py
nestipy_dynamic_module/module/interface.py
nestipy_dynamic_module-0.1.7.dist-info/LICENSE
nestipy_dynamic_module-0.1.7.dist-info/METADATA
nestipy_dynamic_module-0.1.7.dist-info/WHEEL
nestipy_dynamic_module-0.1.7.dist-info/RECORD
